keyapi
